[[1.79773,{"lines":{"0":[["                                                                                                                                              ",{}]],"1":[["                                                                                                                                              ",{}]],"2":[["                                                                                                                                              ",{}]],"3":[["                                                                                                                                              ",{}]],"4":[["                                                                                                                                              ",{}]],"5":[["                                                                                                                                              ",{}]],"6":[["                                                                                                                                              ",{}]],"7":[["                                                                                                                                              ",{}]],"8":[["                                                                                                                                              ",{}]],"9":[["                                                                                                                                              ",{}]],"10":[["                                                                                                                                              ",{}]],"11":[["                                                                                                                                              ",{}]],"12":[["                                                                                                                                              ",{}]],"13":[["                                                                                                                                              ",{}]],"14":[["                                                                                                                                              ",{}]],"15":[["                                                                                                                                              ",{}]],"16":[["                                                                                                                                              ",{}]],"17":[["                                                                                                                                              ",{}]],"18":[["                                                                                                                                              ",{}]],"19":[["                                                                                                                                              ",{}]],"20":[["                                                                                                                                              ",{}]],"21":[["                                                                                                                                              ",{}]],"22":[["                                                                                                                                              ",{}]],"23":[["                                                                                                                                              ",{}]],"24":[["                                                                                                                                              ",{}]],"25":[["                                                                                                                                              ",{}]],"26":[["                                                                                                                                              ",{}]],"27":[["                                                                                                                                              ",{}]],"28":[["                                                                                                                                              ",{}]],"29":[["                                                                                                                                              ",{}]],"30":[["                                                                                                                                              ",{}]],"31":[["                                                                                                                                              ",{}]],"32":[["                                                                                                                                              ",{}]],"33":[["                                                                                                                                              ",{}]],"34":[["                                                                                                                                              ",{}]],"35":[["                                                                                                                                              ",{}]],"36":[["                                                                                                                                              ",{}]],"37":[["                                                                                                                                              ",{}]]},"cursor":{"x":0,"y":0,"visible":true}}],[0.010249,{"lines":{"0":[["~",{"fg":6}],[" ",{}],["❯",{"fg":1,"bold":true}],["❯",{"fg":3,"bold":true}],["❯",{"fg":2,"bold":true}],["                                                                                                                                         ",{}]]},"cursor":{"x":6}}],[8.733078000000001,{"lines":{"0":[["~",{"fg":6}],[" ",{}],["❯",{"fg":1,"bold":true}],["❯",{"fg":3,"bold":true}],["❯",{"fg":2,"bold":true}],[" l                                                                                                                                       ",{}]]},"cursor":{"x":7}}],[0.098151,{"lines":{"0":[["~",{"fg":6}],[" ",{}],["❯",{"fg":1,"bold":true}],["❯",{"fg":3,"bold":true}],["❯",{"fg":2,"bold":true}],[" ls                                                                                                                                      ",{}]]},"cursor":{"x":8}}],[0.239781,{"cursor":{"x":9}}],[0.865158,{"lines":{"0":[["~",{"fg":6}],[" ",{}],["❯",{"fg":1,"bold":true}],["❯",{"fg":3,"bold":true}],["❯",{"fg":2,"bold":true}],[" ls -                                                                                                                                    ",{}]]},"cursor":{"x":10}}],[0.206776,{"lines":{"0":[["~",{"fg":6}],[" ",{}],["❯",{"fg":1,"bold":true}],["❯",{"fg":3,"bold":true}],["❯",{"fg":2,"bold":true}],[" ls -a                                                                                                                                   ",{}]]},"cursor":{"x":11}}],[0.177705,{"cursor":{"x":0,"y":1}}],[0.048917,{"lines":{"1":[[".",{"fg":4,"bold":true}],["          ",{}],["Descargas",{"fg":4,"bold":true}],["        ",{}],[".kde",{"fg":4,"bold":true}],["        ",{}],[".pulse",{"fg":4,"bold":true}],["       ",{}],[".zprezto",{"fg":4,"bold":true}],["       .dmrc            .sudo_as_admin_successful  ",{}],[".zlogin",{"fg":6,"bold":true}],["                       ",{}]]},"cursor":{"x":119}}],[0.008514000000000001,{"lines":{"2":[["..",{"fg":4,"bold":true}],["         ",{}],["Documentos",{"fg":4,"bold":true}],["       ",{}],[".local",{"fg":4,"bold":true}],["      ",{}],["scripts",{"fg":4,"bold":true}],["      ",{}],["zsh",{"fg":4,"bold":true}],["            .esd_auth        .Xauthority                ",{}],[".zlogout",{"fg":6,"bold":true}],["                      ",{}]],"3":[[".ascii.io",{"fg":4,"bold":true}],["  ",{}],["Escritorio",{"fg":4,"bold":true}],["       ",{}],[".mozilla",{"fg":4,"bold":true}],["    ",{}],[".subversion",{"fg":4,"bold":true}],["  .bash_history  .gtkrc-2.0-kde4  .xsession-errors           ",{}],[".zpreztorc",{"fg":6,"bold":true}],["                    ",{}]],"4":[[".cache",{"fg":4,"bold":true}],["     ",{}],["freedownload",{"fg":4,"bold":true}],["     ",{}],["Música",{"fg":4,"bold":true}],["      ",{}],[".thumbnails",{"fg":4,"bold":true}],["  .bash_logout   .histfile        .zcompdump                 ",{}],[".zprofile",{"fg":6,"bold":true}],["                     ",{}]],"5":[[".config",{"fg":4,"bold":true}],["    ",{}],[".gstreamer-0.10",{"fg":4,"bold":true}],["  ",{}],["Plantillas",{"fg":4,"bold":true}],["  ",{}],["Vídeos",{"fg":4,"bold":true}],["       .bashrc        .profile         .zcompdump.zwc             ",{}],[".zshenv",{"fg":6,"bold":true}],["                       ",{}]],"6":[[".dbus",{"fg":4,"bold":true}],["      ",{}],["Imágenes",{"fg":4,"bold":true}],["         ",{}],["Público",{"fg":4,"bold":true}],["     ",{}],[".zpresto",{"fg":4,"bold":true}],["     .cvspass       .pulse-cookie    .zhistory                  ",{}],[".zshrc",{"fg":6,"bold":true}],["                        ",{}]],"7":[["~",{"fg":6}],[" ",{}],["❯",{"fg":1,"bold":true}],["❯",{"fg":3,"bold":true}],["❯",{"fg":2,"bold":true}],["                                                                                                                                         ",{}]]},"cursor":{"x":6,"y":7}}],[7.205716,{"cursor":{"x":0,"y":8}}]]